{
  "item": {
    "title": "吴越府8幢、16幢",
    "url": "https://www.hz-notary.com/lottery/detail?lottery.id=011a6543556d4fc8a0a49566c9e8ee6d",
    "datetime": "2018-12-29 08:35:16"
  },
  "lottery": {
    "url": "https://www.hz-notary.com/lottery/detail?lottery.id=011a6543556d4fc8a0a49566c9e8ee6d",
    "items": [
      {
        "title": "公 告",
        "url": "https://www.hz-notary.com/lottery/detail_content?lotteryContent.id=8c04b9bf1fd144f3a0c2e0237d6cedb3",
        "datetime": "2018-12-29 08:35:55"
      },
      {
        "title": "吴越府8幢、16幢 购房意向登记汇总表",
        "url": "https://www.hz-notary.com/lottery/detail_content?lotteryContent.id=9cf8693f95904f3694fdb5060c070b97",
        "datetime": "2018-12-29 08:38:30"
      }
    ]
  },
  "summary": "http://down.hz-notary.com:10006/pdf/2019/0117/190117152910964_2094727808902251.pdf"
}