{
  "item": {
    "title": "观唐花园二期S26幢、S27幢、S28幢",
    "url": "https://www.hz-notary.com/lottery/detail?lottery.id=0c3818b590744e9ca87b27d1303412e2",
    "datetime": "2018-12-20 15:50:48"
  },
  "lottery": {
    "url": "https://www.hz-notary.com/lottery/detail?lottery.id=0c3818b590744e9ca87b27d1303412e2",
    "items": [
      {
        "title": "公 告",
        "url": "https://www.hz-notary.com/lottery/detail_content?lotteryContent.id=b916208f10554986a3db6a6216614a4a",
        "datetime": "2018-12-20 15:51:22"
      },
      {
        "title": "观唐花园二期S26幢、S27幢、S28幢 购房意向登记汇总表",
        "url": "https://www.hz-notary.com/lottery/detail_content?lotteryContent.id=e7290d501b1e4d6bbee989b162baa9c7",
        "datetime": "2018-12-20 15:54:18"
      }
    ]
  },
  "summary": "http://down.hz-notary.com:10006/pdf/2018/1220/181220155400987_8017970916467911.pdf"
}