{
  "item": {
    "title": "中天珺府94、95幢",
    "url": "https://www.hz-notary.com/lottery/detail?lottery.id=2f9c03eb92bb409d8bdd4eef6f9af904",
    "datetime": "2019-04-25 08:23:51"
  },
  "lottery": {
    "url": "https://www.hz-notary.com/lottery/detail?lottery.id=2f9c03eb92bb409d8bdd4eef6f9af904",
    "items": [
      {
        "title": "“中天珺府94、95幢”购房意向登记汇总表",
        "url": "https://www.hz-notary.com/lottery/detail_content?lotteryContent.id=04aab8efeade455cb53f776ecd672b3c",
        "datetime": "2019-04-25 08:31:20"
      },
      {
        "title": "“中天珺府94、95幢”公开销售公证摇号结果",
        "url": "https://www.hz-notary.com/lottery/detail_content?lotteryContent.id=5fdd2c1f72614410ab35dcbf4c9809a5",
        "datetime": "2019-04-26 08:49:41"
      },
      {
        "title": "“中天珺府94、95幢”公开销售公证摇号公告",
        "url": "https://www.hz-notary.com/lottery/detail_content?lotteryContent.id=c6cbb7e589b246248e0e5c3494dd45a5",
        "datetime": "2019-04-25 08:24:11"
      }
    ]
  },
  "summary": "http://down.hz-notary.com:10006/pdf/2019/0425/190425083054241_10536829753593968.pdf",
  "result": "http://down.hz-notary.com:10006/pdf/2019/0426/190426084935101_10624350994888836.pdf"
}