{
  "item": {
    "title": "星汇花园",
    "url": "https://www.hz-notary.com/lottery/detail?lottery.id=402940ecbb304dcc927bf10d4a389dca",
    "datetime": "2018-05-05 09:57:13"
  },
  "lottery": {
    "url": "https://www.hz-notary.com/lottery/detail?lottery.id=402940ecbb304dcc927bf10d4a389dca",
    "items": [
      {
        "title": "“青山湖街道星汇花园28幢”公开销售摇号公告",
        "url": "https://www.hz-notary.com/lottery/detail_content?lotteryContent.id=2de292759ef34b7e958d98e7f553bc1d",
        "datetime": "2018-05-05 09:57:49"
      },
      {
        "title": "“青山湖街道星汇花园28幢”公开销售摇号结果",
        "url": "https://www.hz-notary.com/lottery/detail_content?lotteryContent.id=6e56dd50c33a433bb1e9eabe72afc4eb",
        "datetime": "2018-05-07 14:28:32"
      },
      {
        "title": "“青山湖街道星汇花园28幢”购房意向登记汇总表",
        "url": "https://www.hz-notary.com/lottery/detail_content?lotteryContent.id=98ecfabd279947649e26577992629a5d",
        "datetime": "2018-05-05 10:00:09"
      },
      {
        "title": "“青山湖街道星汇花园28幢”公开销售公证摇号现场回放",
        "url": "https://www.hz-notary.com/lottery/detail_content?lotteryContent.id=aaaf63ffd4764c269837b140589c343e",
        "datetime": "2018-05-07 16:00:40"
      }
    ]
  },
  "summary": "https://www.hz-notary.com/ueditor/jsp/upload/file/20180505/1525485730754011733.pdf",
  "result": "https://www.hz-notary.com/ueditor/jsp/upload/file/20180507/1525674497413056955.pdf"
}