{
  "item": {
    "title": "星未来云邸1、2、3号楼",
    "url": "https://www.hz-notary.com/lottery/detail?lottery.id=4f71d0b2c1244afc8c0f01816252efaf",
    "datetime": "2019-01-07 09:11:18"
  },
  "lottery": {
    "url": "https://www.hz-notary.com/lottery/detail?lottery.id=4f71d0b2c1244afc8c0f01816252efaf",
    "items": [
      {
        "title": "星未来云邸1、2、3号楼 购房意向登记汇总表",
        "url": "https://www.hz-notary.com/lottery/detail_content?lotteryContent.id=843d4fed3f5940549a174d78cc3eeed6",
        "datetime": "2019-01-07 13:35:57"
      },
      {
        "title": "公 告",
        "url": "https://www.hz-notary.com/lottery/detail_content?lotteryContent.id=95152c8fe7af444ea38e88c81425148b",
        "datetime": "2019-01-07 09:11:42"
      }
    ]
  },
  "summary": "http://down.hz-notary.com:10006/pdf/2019/0107/190107133540876_1223916978948920.pdf"
}