{
  "item": {
    "title": "泰杭院1幢、7幢、11幢、21幢",
    "url": "https://www.hz-notary.com/lottery/detail?lottery.id=783d572664674e038015eaad60bfb090",
    "datetime": "2018-05-21 14:36:39"
  },
  "lottery": {
    "url": "https://www.hz-notary.com/lottery/detail?lottery.id=783d572664674e038015eaad60bfb090",
    "items": [
      {
        "title": "公  告",
        "url": "https://www.hz-notary.com/lottery/detail_content?lotteryContent.id=00ad0b7430844185bd20dbb05573048d",
        "datetime": "2018-05-21 14:37:00"
      },
      {
        "title": "泰杭院1#、7#、11#、21#购房意向登记汇总表",
        "url": "https://www.hz-notary.com/lottery/detail_content?lotteryContent.id=e53aba15461b4124bc295e0cd2573c98",
        "datetime": "2018-05-21 14:39:17"
      }
    ]
  },
  "summary": "https://www.hz-notary.com/ueditor/jsp/upload/file/20180521/1526884935759007654.pdf"
}