{
  "item": {
    "title": "悦江府6、11幢",
    "url": "https://www.hz-notary.com/lottery/detail?lottery.id=887f84ead861482784919c3fc2ceaf3e",
    "datetime": "2019-05-04 09:10:22"
  },
  "lottery": {
    "url": "https://www.hz-notary.com/lottery/detail?lottery.id=887f84ead861482784919c3fc2ceaf3e",
    "items": [
      {
        "title": "“悦江府6、11幢”公开销售摇号结果",
        "url": "https://www.hz-notary.com/lottery/detail_content?lotteryContent.id=8d13a739287e44d385e6a44d8068ea99",
        "datetime": "2019-05-05 10:18:58"
      },
      {
        "title": "“悦江府6、11幢”购房意向登记汇总表",
        "url": "https://www.hz-notary.com/lottery/detail_content?lotteryContent.id=956f39e5899d4bd7857c11b58161f61a",
        "datetime": "2019-05-04 09:30:24"
      },
      {
        "title": "“悦江府6、11幢”公开销售摇号公告",
        "url": "https://www.hz-notary.com/lottery/detail_content?lotteryContent.id=a273df9283c643e69d17997748823fe6",
        "datetime": "2019-05-04 09:10:47"
      }
    ]
  },
  "summary": "http://down.hz-notary.com:10006/pdf/2019/0504/190504093001616_11317978532189311.pdf",
  "result": "http://down.hz-notary.com:10006/pdf/2019/0505/190505101852195_11407309215817358.pdf"
}