{
  "item": {
    "title": "水云城5、11、12、13号楼",
    "url": "https://www.hz-notary.com/lottery/detail?lottery.id=92e01fea63f9401286c41ff633e7df23",
    "datetime": "2019-03-13 08:40:16"
  },
  "lottery": {
    "url": "https://www.hz-notary.com/lottery/detail?lottery.id=92e01fea63f9401286c41ff633e7df23",
    "items": [
      {
        "title": "水云城5、11、12、13号楼 购房意向登记汇总表",
        "url": "https://www.hz-notary.com/lottery/detail_content?lotteryContent.id=7ba89b521fbc474e9a89585548a90bb7",
        "datetime": "2019-03-13 08:45:27"
      },
      {
        "title": "公告",
        "url": "https://www.hz-notary.com/lottery/detail_content?lotteryContent.id=b02dca50e0374d4bb13eea9a7dd4a36c",
        "datetime": "2019-03-13 08:41:23"
      }
    ]
  },
  "summary": "http://down.hz-notary.com:10006/pdf/2019/0313/190313084515806_6822492022587495.pdf"
}