{
  "item": {
    "title": "银塆学府14幢",
    "url": "https://www.hz-notary.com/lottery/detail?lottery.id=946f499cbf7a4d8fb39c7fc86ee7ade9",
    "datetime": "2018-08-05 08:52:59"
  },
  "lottery": {
    "url": "https://www.hz-notary.com/lottery/detail?lottery.id=946f499cbf7a4d8fb39c7fc86ee7ade9",
    "items": [
      {
        "title": "“银塆学府14幢”购房意向登记汇总表",
        "url": "https://www.hz-notary.com/lottery/detail_content?lotteryContent.id=0d2918fad6554f55b57c5babb54fc6b4",
        "datetime": "2018-08-05 08:55:38"
      },
      {
        "title": "“银塆学府14幢”公开销售摇号结果",
        "url": "https://www.hz-notary.com/lottery/detail_content?lotteryContent.id=368c584d02754a99a186ca54e825d8b4",
        "datetime": "2018-08-06 10:04:58"
      },
      {
        "title": "“银塆学府14幢”公开销售摇号公告",
        "url": "https://www.hz-notary.com/lottery/detail_content?lotteryContent.id=9fc5ddef023a4951a7a64f3777cea94c",
        "datetime": "2018-08-05 08:53:51"
      }
    ]
  },
  "summary": "http://down.hz-notary.com:10006/pdf/2018/0805/180805085453842_3169665720389252.pdf",
  "result": "http://down.hz-notary.com:10006/pdf/2018/0806/180806100420843_3260235974541240.pdf"
}