{
  "item": {
    "title": "玉润钱潮府2幢、3幢",
    "url": "https://www.hz-notary.com/lottery/detail?lottery.id=9d2ad5c12b894c5aae962760521b0d00",
    "datetime": "2018-12-15 21:00:20"
  },
  "lottery": {
    "url": "https://www.hz-notary.com/lottery/detail?lottery.id=9d2ad5c12b894c5aae962760521b0d00",
    "items": [
      {
        "title": "“玉润钱潮府2幢、3幢”公开销售摇号结果",
        "url": "https://www.hz-notary.com/lottery/detail_content?lotteryContent.id=7bfec63e0ea94e49b3045a55f40b96aa",
        "datetime": "2018-12-17 09:19:17"
      },
      {
        "title": "“玉润钱潮府2幢、3幢”购房意向登记汇总表",
        "url": "https://www.hz-notary.com/lottery/detail_content?lotteryContent.id=9a5deae6b1044a38ab65ffe3d0dc3e67",
        "datetime": "2018-12-15 21:52:02"
      },
      {
        "title": "“玉润钱潮府2幢、3幢”公开销售摇号公告",
        "url": "https://www.hz-notary.com/lottery/detail_content?lotteryContent.id=9bffcca7c74d45edb8044cb39291ac64",
        "datetime": "2018-12-15 21:00:52"
      }
    ]
  },
  "summary": "http://down.hz-notary.com:10006/pdf/2018/1215/181215215144224_7607434023482359.pdf",
  "result": "http://down.hz-notary.com:10006/pdf/2018/1217/181217091911470_7735081102407879.pdf"
}