{
  "item": {
    "title": "嘉悦府30、31、33、37幢",
    "url": "https://www.hz-notary.com/lottery/detail?lottery.id=bd8476d2c0ab4303927b332489ff8876",
    "datetime": "2018-12-04 09:51:40"
  },
  "lottery": {
    "url": "https://www.hz-notary.com/lottery/detail?lottery.id=bd8476d2c0ab4303927b332489ff8876",
    "items": [
      {
        "title": "“嘉悦府30、31、33、37幢”公开销售公证摇号结果",
        "url": "https://www.hz-notary.com/lottery/detail_content?lotteryContent.id=0d86d68fb4494f0895155fa5f952a4fd",
        "datetime": "2018-12-05 10:52:33"
      },
      {
        "title": "“嘉悦府30、31、33、37幢”购房意向登记汇总表",
        "url": "https://www.hz-notary.com/lottery/detail_content?lotteryContent.id=ae51f88079df4795bb6169a0f2023154",
        "datetime": "2018-12-04 09:53:07"
      },
      {
        "title": "“嘉悦府30、31、33、37幢”公开销售公证摇号公告",
        "url": "https://www.hz-notary.com/lottery/detail_content?lotteryContent.id=dc256df93f1f4a249934b7c7f46d6d2b",
        "datetime": "2018-12-04 09:52:51"
      }
    ]
  },
  "summary": "http://down.hz-notary.com:10006/pdf/2018/1204/181204100128755_6614418531367827.pdf",
  "result": "http://down.hz-notary.com:10006/pdf/2018/1205/181205105219976_6703869840656149.pdf"
}