{
  "item": {
    "title": "风尚望和湾1、4号楼",
    "url": "https://www.hz-notary.com/lottery/detail?lottery.id=d3d21d6504c54ffb96b2a9faab48e26e",
    "datetime": "2019-09-26 18:00:43"
  },
  "lottery": {
    "url": "https://www.hz-notary.com/lottery/detail?lottery.id=d3d21d6504c54ffb96b2a9faab48e26e",
    "items": [
      {
        "title": "“风尚望和湾1、4号楼”公开销售摇号结果",
        "url": "https://www.hz-notary.com/lottery/detail_content?lotteryContent.id=3e2455e18c704effb1dce81506b56d17",
        "datetime": "2019-09-27 18:17:31"
      },
      {
        "title": "“风尚望和湾1、4号楼”公开销售摇号公告",
        "url": "https://www.hz-notary.com/lottery/detail_content?lotteryContent.id=5f7aceddbeef4a2ca212a7dd3f4bb794",
        "datetime": "2019-09-26 18:00:51"
      },
      {
        "title": "“风尚望和湾1、4号楼”购房意向登记汇总表",
        "url": "https://www.hz-notary.com/lottery/detail_content?lotteryContent.id=df193df2955042e8b00e6c2ec5a74e46",
        "datetime": "2019-09-26 18:01:04"
      }
    ]
  },
  "summary": "http://down.hz-notary.com:10006/pdf/2019/0926/190926180507904_23876891314902503.pdf",
  "result": "http://down.hz-notary.com:10006/pdf/2019/0927/190927181718514_23964022163922206.pdf"
}