{
  "item": {
    "title": "翡翠之星公寓5、7幢",
    "url": "https://www.hz-notary.com/lottery/detail?lottery.id=d58d2874d5054bcfa2e70efdb94b5c5a",
    "datetime": "2018-11-10 23:40:25"
  },
  "lottery": {
    "url": "https://www.hz-notary.com/lottery/detail?lottery.id=d58d2874d5054bcfa2e70efdb94b5c5a",
    "items": [
      {
        "title": "“翡翠之星公寓5、7幢”公开销售公证摇号结果",
        "url": "https://www.hz-notary.com/lottery/detail_content?lotteryContent.id=24f57b656f1e4845b14ed18758d06c42",
        "datetime": "2018-11-12 09:50:26"
      },
      {
        "title": "“翡翠之星公寓5、7幢”购房意向登记汇总表",
        "url": "https://www.hz-notary.com/lottery/detail_content?lotteryContent.id=8d8dce89715e4108aa0141c28e6de82d",
        "datetime": "2018-11-10 23:43:24"
      },
      {
        "title": "“翡翠之星公寓5、7幢”公开销售公证摇号公告",
        "url": "https://www.hz-notary.com/lottery/detail_content?lotteryContent.id=ba171d2248c74eb6a3978df1598e6ad7",
        "datetime": "2018-11-10 23:42:12"
      }
    ]
  },
  "summary": "http://down.hz-notary.com:10006/pdf/2018/1110/181110234255731_4590105074104048.pdf",
  "result": "http://down.hz-notary.com:10006/pdf/2018/1112/181112095017801_4712947747639027.pdf"
}