{
  "item": {
    "title": "相贤府18号楼",
    "url": "https://www.hz-notary.com/lottery/detail?lottery.id=f254d3e33cc94c0b997c3a8aff4ebeab",
    "datetime": "2019-04-12 08:25:43"
  },
  "lottery": {
    "url": "https://www.hz-notary.com/lottery/detail?lottery.id=f254d3e33cc94c0b997c3a8aff4ebeab",
    "items": [
      {
        "title": "“相贤府18号楼”公开销售摇号结果",
        "url": "https://www.hz-notary.com/lottery/detail_content?lotteryContent.id=1504316570e541279c0d02322e3305e0",
        "datetime": "2019-04-13 13:48:59"
      },
      {
        "title": "“相贤府18号楼”购房意向登记汇总表",
        "url": "https://www.hz-notary.com/lottery/detail_content?lotteryContent.id=3c5e3aa3606949658be0ca3679e79ce6",
        "datetime": "2019-04-12 08:32:56"
      },
      {
        "title": "“相贤府18号楼”公开销售摇号公告",
        "url": "https://www.hz-notary.com/lottery/detail_content?lotteryContent.id=ad60e14bde9d498a9fe3fc1d47830af3",
        "datetime": "2019-04-12 08:26:14"
      }
    ]
  },
  "summary": "http://down.hz-notary.com:10006/pdf/2019/0412/190412083240471_9413735940677793.pdf",
  "result": "http://down.hz-notary.com:10006/pdf/2019/0413/190413134851487_9519107480076755.pdf"
}