{
  "item": {
    "title": "云悦湾10幢、11幢",
    "url": "https://www.hz-notary.com/lottery/detail?lottery.id=f480925286b84810945e6ad008f8c151",
    "datetime": "2019-10-08 08:56:16"
  },
  "lottery": {
    "url": "https://www.hz-notary.com/lottery/detail?lottery.id=f480925286b84810945e6ad008f8c151",
    "items": [
      {
        "title": "“云悦湾10幢、11幢”购房意向登记汇总表",
        "url": "https://www.hz-notary.com/lottery/detail_content?lotteryContent.id=569d49108a904e1bbf92ee29f9361e03",
        "datetime": "2019-10-08 09:00:49"
      },
      {
        "title": "“云悦湾10幢、11幢”公开销售公证摇号公告",
        "url": "https://www.hz-notary.com/lottery/detail_content?lotteryContent.id=ae3ce554d371438c910f262c5bf11364",
        "datetime": "2019-10-08 08:56:34"
      }
    ]
  },
  "summary": "http://down.hz-notary.com:10006/pdf/2019/1008/191008085859295_24880925531293636.pdf"
}