{
  "item": {
    "title": "星悦城19幢",
    "url": "https://www.hz-notary.com/lottery/detail?lottery.id=ff1b5c2b82214da092db4de9b6dea724",
    "datetime": "2019-02-22 09:21:56"
  },
  "lottery": {
    "url": "https://www.hz-notary.com/lottery/detail?lottery.id=ff1b5c2b82214da092db4de9b6dea724",
    "items": [
      {
        "title": "星悦城19幢 购房意向登记汇总表",
        "url": "https://www.hz-notary.com/lottery/detail_content?lotteryContent.id=28d0ce165dc14aaaa1b07a751f5403a3",
        "datetime": "2019-02-22 09:24:12"
      },
      {
        "title": "公告",
        "url": "https://www.hz-notary.com/lottery/detail_content?lotteryContent.id=f25564573fee49728127cdc6f23ad3e9",
        "datetime": "2019-02-22 09:22:16"
      }
    ]
  },
  "summary": "http://down.hz-notary.com:10006/pdf/2019/0222/190222092352255_5183210517342960.pdf"
}